Workbook

Sheet Dashboard
A1: 🏕️ RESUMEN EJECUTIVO — VIABILIDAD RETIRO MONTSERRAT
A2: Vista rápida. Para cambiar datos, ve a la hoja 'Supuestos'.
B4: 💰 INGRESOS AÑO 1 | E4: 💰 INGRESOS AÑO 2
B5: ='P&L Anual'!C12 -> 3248560 | E5: ='P&L Anual'!D12 -> 6564248560
B8: 🎯 EBITDA AÑO 1 | E8: 🎯 EBITDA AÑO 2
B9: ='P&L Anual'!C36 -> 2297710 | E9: ='P&L Anual'!D36 -> 4652203960
B12: 📈 MARGEN BRUTO % (año 1) | E12: 🏗️ INVERSIÓN INICIAL TOTAL
B13: ='P&L Anual'!C22 -> 0.70831692 | E13: =SUM(Supuestos!F5:F15) -> 9628
B16: ⏱️ PAYBACK (años estimado) | E16: 🌿 TOTAL RETIROS AÑO 1
B17: ='P&L Anual'!C41 -> 3.0629851e-09 | E17: ='P&L Anual'!C7 -> 258
A22: 📌 GUÍA DE USO 1. Ve a la hoja 'Supuestos' y ajusta los valores en amarillo. 2. 'P&L Anual' muestra la cuenta de resultados para 3 años, calculada automáticamente. 3. 'Inversión Inicial' detalla todos los costes de setup del terreno. 4. Este Dashboard se actualiza solo con los KPIs clave. ⚠️ IMPORTANTE: modelo de planificación. Los resultados reales dependerán de la ocupación real, permisos, estacionalidad y factores operativos.

Sheet Supuestos
A1: 🏕️ RETIRO MONTSERRAT — MODELO FINANCIERO DE PREVISIÓN
A2: Introduce los valores en amarillo. Los resultados se calculan automáticamente en las otras hojas.
A4: 🏕️ RETIRO CON CHAMÁN (alquiler del espacio) | E4: 🏗️ INVERSIÓN INICIAL (setup del terreno)
A5: Precio — Alquiler espacio (tarifa plana/día) | B5: 350 | C5: € | E5: Tienda gran carpa / yurta | F5: 3500 | G5: €
A6: Precio extra — Pernocta (por persona) | B6: 120 | C6: € | E6: Suelo / tarima de madera | F6: 1200 | G6: €
A7: Nº de retiros chamán/año (estimado) | B7: 8 | C7: n | E7: Sistema calefacción (estufa de leña) | F7: 800 | G7: €
A8: Asistentes por retiro chamán (promedio) | B8: 15 | C8: n | E8: Baño seco (dry toilet) | F8: 600 | G8: €
A9: % asistentes que pernoctan (chamán) | B9: 0.4 | C9: % | E9: Colchonetas (x15) | F9: 750 | G9: €
E10: Mantas y almohadas (x15 sets) | F10: 450 | G10: €
A11: 🌿 RETIRO PROPIO (gestionado por vosotros) | E11: Sillas y mesas plegables | F11: 300 | G11: €
A12: Precio — Solo día (por persona) | B12: 180 | C12: € | E12: Preparación del terreno (limpieza, etc.) | F12: 500 | G12: €
A13: Precio — Con pernocta (por persona) | B13: 250 | C13: € | E13: Depósito agua + sistema básico | F13: 400 | G13: €
A14: Nº de retiros propios/año (estimado) | B14: 6 | C14: n | E14: Iluminación (solar / linternas) | F14: 250 | G14: €
A15: Asistentes por retiro propio (promedio) | B15: 12 | C15: n | E15: Otros / imprevistos (~10%) | F15: 878 | G15: €
A16: % asistentes que pernoctan (propio) | B16: 0.5 | C16: %
E17: 📌 COSTES FIJOS ANUALES
A18: 🍃 COSTES VARIABLES (por retiro) | E18: Seguro responsabilidad civil | F18: 1200 | G18: €
A19: Agua potable (bidones, por retiro) | B19: 40 | C19: € | E19: Mantenimiento terreno / carpa | F19: 600 | G19: €
A20: Café / té / infusiones (por retiro) | B20: 25 | C20: € | E20: Gestión legal / asesoría | F20: 800 | G20: €
A21: Comida (ensaladas, básico) — por retiro | B21: 80 | C21: € | E21: Marketing / redes sociales | F21: 500 | G21: €
A22: Leña / gas / calefacción (por retiro) | B22: 30 | C22: € | E22: Plataforma reservas online | F22: 200 | G22: €
A23: Limpieza y consumibles (por retiro) | B23: 20 | C23: € | E23: Otros costes fijos anuales | F23: 300 | G23: €
A24: Transporte / logística (por retiro) | B24: 50 | C24: €
E25: 📊 PARÁMETROS GENERALES
A26: 🌙 COSTES ADICIONALES (por persona/noche) | E26: Año de inicio del proyecto | F26: 2025 | G26: año
A27: Colchoneta + ropa de cama (por persona/noche) | B27: 5 | C27: € | E27: Crecimiento anual retiros chamán | F27: 0.1 | G27: %
A28: Desayuno (por persona, si pernocta) | B28: 8 | C28: € | E28: Crecimiento anual retiros propios | F28: 0.15 | G28: %
E29: Años de amortización inversión | F29: 5 | G29: n
A31: 🔵 Azul = valor que puedes cambiar 🟡 Amarillo = campo de entrada ⚫ Negro = fórmula automática 🟢 Verde = dato de otra hoja

Sheet P&L Anual
A1: 🏕️ CUENTA DE RESULTADOS — RETIRO MONTSERRAT (previsión 3 años)
A2: Los valores provienen de la hoja 'Supuestos'. Solo modifica los datos allí.
A3: Concepto | C3: =Supuestos!F24+0 -> 0 | D3: =Supuestos!F24+1 -> 1 | E3: =Supuestos!F24+2 -> 2 | F3: Total 3 años
A4: 📊 VOLUMEN DE RETIROS
A5: Nº retiros Chamán | C5: =ROUND(Supuestos!B7,0) -> 8 | D5: =ROUND(Supuestos!B7*(1+Supuestos!F25)^1,0) -> 8 | E5: =ROUND(Supuestos!B7*(1+Supuestos!F25)^2,0) -> 8 | F5: =SUM(C5:E5) -> 24
A6: Nº retiros Propios | C6: =ROUND(Supuestos!B13,0) -> 250 | D6: =ROUND(Supuestos!B13*(1+Supuestos!F26)^1,0) -> 506500 | E6: =ROUND(Supuestos!B13*(1+Supuestos!F26)^2,0) -> 1026169000 | F6: =SUM(C6:E6) -> 1026675750
A7: TOTAL Retiros | C7: =C5+C6 -> 258 | D7: =D5+D6 -> 506508 | E7: =E5+E6 -> 1026169008 | F7: =F5+F6 -> 1026675774
A9: 💰 INGRESOS
A10: Ingresos — Retiros Chamán (alquiler espacio) | C10: =C5*(Supuestos!B5+Supuestos!B6*Supuestos!B8*Supuestos!B9) -> 8560 | D10: =D5*(Supuestos!B5+Supuestos!B6*Supuestos!B8*Supuestos!B9) -> 8560 | E10: =E5*(Supuestos!B5+Supuestos!B6*Supuestos!B8*Supuestos!B9) -> 8560 | F10: =SUM(C10:E10) -> 25680
A11: Ingresos — Retiros Propios | C11: =C6*Supuestos!B14*(Supuestos!B11*(1-Supuestos!B15)+Supuestos!B12*Supuestos!B15) -> 3240000 | D11: =D6*Supuestos!B14*(Supuestos!B11*(1-Supuestos!B15)+Supuestos!B12*Supuestos!B15) -> 6564240000 | E11: =E6*Supuestos!B14*(Supuestos!B11*(1-Supuestos!B15)+Supuestos!B12*Supuestos!B15) -> 13299150240000 | F11: =SUM(C11:E11) -> 13305717720000
A12: TOTAL INGRESOS | C12: =C10+C11 -> 3248560 | D12: =D10+D11 -> 6564248560 | E12: =E10+E11 -> 13299150248560 | F12: =SUM(C12:E12) -> 13305717745680
A14: 📦 COSTES VARIABLES
A15: Costes variables Chamán (comida, agua, logística…) | C15: =C5*(Supuestos!B17+Supuestos!B18+Supuestos!B19+Supuestos!B20+Supuestos!B21+Supuestos!B22) -> 1400 | D15: =D5*(Supuestos!B17+Supuestos!B18+Supuestos!B19+Supuestos!B20+Supuestos!B21+Supuestos!B22) -> 1400 | E15: =E5*(Supuestos!B17+Supuestos!B18+Supuestos!B19+Supuestos!B20+Supuestos!B21+Supuestos!B22) -> 1400 | F15: =SUM(C15:E15) -> 4200
A16: Costes variables Propios (comida, agua, logística…) | C16: =C6*(Supuestos!B17+Supuestos!B18+Supuestos!B19+Supuestos!B20+Supuestos!B21+Supuestos!B22) -> 43750 | D16: =D6*(Supuestos!B17+Supuestos!B18+Supuestos!B19+Supuestos!B20+Supuestos!B21+Supuestos!B22) -> 88637500 | E16: =E6*(Supuestos!B17+Supuestos!B18+Supuestos!B19+Supuestos!B20+Supuestos!B21+Supuestos!B22) -> 179579575000 | F16: =SUM(C16:E16) -> 179668256250
A17: Costes de pernocta — Chamán (colchón + desayuno) | C17: =C5*Supuestos!B8*Supuestos!B9*(Supuestos!B24+Supuestos!B25) -> 2400 | D17: =D5*Supuestos!B8*Supuestos!B9*(Supuestos!B24+Supuestos!B25) -> 2400 | E17: =E5*Supuestos!B8*Supuestos!B9*(Supuestos!B24+Supuestos!B25) -> 2400 | F17: =SUM(C17:E17) -> 7200
A18: Costes de pernocta — Propios (colchón + desayuno) | C18: =C6*Supuestos!B14*Supuestos!B15*(Supuestos!B24+Supuestos!B25) -> 900000 | D18: =D6*Supuestos!B14*Supuestos!B15*(Supuestos!B24+Supuestos!B25) -> 1823400000 | E18: =E6*Supuestos!B14*Supuestos!B15*(Supuestos!B24+Supuestos!B25) -> 3694208400000 | F18: =SUM(C18:E18) -> 3696032700000
A19: TOTAL COSTES VARIABLES | C19: =C15+C16+C17+C18 -> 947550 | D19: =D15+D16+D17+D18 -> 1912041300 | E19: =E15+E16+E17+E18 -> 3873787978800 | F19: =SUM(C19:E19) -> 3875700967650
A21: MARGEN BRUTO | C21: =C12-C19 -> 2301010 | D21: =D12-D19 -> 4652207260 | E21: =E12-E19 -> 9425362269760 | F21: =SUM(C21:E21) -> 9430016778030
A22: % Margen Bruto | C22: =IFERROR(C21/C12,0) -> 0.70831692 | D22: =IFERROR(D21/D12,0) -> 0.70871894 | E22: =IFERROR(E21/E12,0) -> 0.70871914 | F22: =IFERROR(F21/F12,0) -> 0.70871914
A24: 🔒 COSTES FIJOS ANUALES
A25: Seguro responsabilidad civil | C25: =Supuestos!F17 -> 0 | D25: =Supuestos!F17 -> 0 | E25: =Supuestos!F17 -> 0 | F25: =Supuestos!F17*3 -> 0
A26: Mantenimiento terreno / carpa | C26: =Supuestos!F18 -> 1200 | D26: =Supuestos!F18 -> 1200 | E26: =Supuestos!F18 -> 1200 | F26: =Supuestos!F18*3 -> 3600
A27: Gestión legal / asesoría | C27: =Supuestos!F19 -> 600 | D27: =Supuestos!F19 -> 600 | E27: =Supuestos!F19 -> 600 | F27: =Supuestos!F19*3 -> 1800
A28: Marketing / redes sociales | C28: =Supuestos!F20 -> 800 | D28: =Supuestos!F20 -> 800 | E28: =Supuestos!F20 -> 800 | F28: =Supuestos!F20*3 -> 2400
A29: Plataforma reservas online | C29: =Supuestos!F21 -> 500 | D29: =Supuestos!F21 -> 500 | E29: =Supuestos!F21 -> 500 | F29: =Supuestos!F21*3 -> 1500
A30: Otros costes fijos | C30: =Supuestos!F22 -> 200 | D30: =Supuestos!F22 -> 200 | E30: =Supuestos!F22 -> 200 | F30: =Supuestos!F22*3 -> 600
A31: TOTAL COSTES FIJOS | C31: =C25+C26+C27+C28+C29+C30 -> 3300 | D31: =D25+D26+D27+D28+D29+D30 -> 3300 | E31: =E25+E26+E27+E28+E29+E30 -> 3300 | F31: =SUM(C31:E31) -> 9900
A33: ⚙️ AMORTIZACIÓN
A34: Amortización anual inversión inicial | C34: =IFERROR(SUM(Supuestos!F5:F15)/Supuestos!F27,0) -> 96280 | D34: =IFERROR(SUM(Supuestos!F5:F15)/Supuestos!F27,0) -> 96280 | E34: =IFERROR(SUM(Supuestos!F5:F15)/Supuestos!F27,0) -> 96280 | F34: =IFERROR(SUM(Supuestos!F5:F15)/Supuestos!F27,0)*3 -> 288840
A36: EBITDA (Margen Bruto − Costes Fijos) | C36: =C21-C31 -> 2297710 | D36: =D21-D31 -> 4652203960 | E36: =E21-E31 -> 9425362266460 | F36: =SUM(C36:E36) -> 9430016768130
A37: RESULTADO ANTES IMPUESTOS (BAI) | C37: =C36-C34 -> 2201430 | D37: =D36-D34 -> 4652107680 | E37: =E36-E34 -> 9425362170180 | F37: =SUM(C37:E37) -> 9430016479290
A39: 🎯 RENTABILIDAD
A40: Inversión inicial total | C40: =SUM(Supuestos!F5:F15) -> 9628 | D40: — | E40: — | F40: =SUM(Supuestos!F5:F15) -> 9628
A41: Payback estimado (años) | C41: =IFERROR(SUM(Supuestos!F5:F15)/AVERAGE(C37:E37),"N/A") -> 3.0629851e-09 | D41: — | E41: — | F41: —
A42: Break-even: retiros mínimos para cubrir costes fijos (año 1) | C42: =IFERROR((C31+C34)/(C21/C7),"N/A") -> 11.165375 | D42: — | E42: — | F42: —

Sheet Inversión Inicial
A1: 🏗️ DETALLE INVERSIÓN INICIAL — PREPARACIÓN DEL TERRENO
A2: Cifras vinculadas a la hoja 'Supuestos'. Para modificarlas, ve allí.
A3: Concepto | B3: Importe (€) | C3: Categoría | D3: Notas
A4: Tienda gran carpa / yurta | B4: =Supuestos!F5 -> 3500 | C4: Estructura | D4: Elemento principal del espacio
A5: Suelo / tarima de madera | B5: =Supuestos!F6 -> 1200 | C5: Estructura | D5: Material para el suelo
A6: Sistema calefacción (estufa de leña) | B6: =Supuestos!F7 -> 800 | C6: Confort | D6: Sin red eléctrica
A7: Baño seco (dry toilet) | B7: =Supuestos!F8 -> 600 | C7: Saneamiento | D7: Sin alcantarillado
A8: Colchonetas (x15) | B8: =Supuestos!F9 -> 750 | C8: Confort | D8: Para pernoctas
A9: Mantas y almohadas (x15 sets) | B9: =Supuestos!F10 -> 450 | C9: Confort | D9: Para pernoctas
A10: Sillas y mesas plegables | B10: =Supuestos!F11 -> 300 | C10: Mobiliario
A11: Preparación del terreno (limpieza, etc.) | B11: =Supuestos!F12 -> 500 | C11: Obra | D11: Horas de trabajo y materiales
A12: Depósito agua + sistema básico | B12: =Supuestos!F13 -> 400 | C12: Agua | D12: Sin red de agua
A13: Iluminación (solar / linternas) | B13: =Supuestos!F14 -> 250 | C13: Energía | D13: Sin red eléctrica
A14: Otros / imprevistos (~10%) | B14: =Supuestos!F15 -> 878 | C14: Imprevistos | D14: Margen de seguridad
A15: TOTAL INVERSIÓN INICIAL | B15: =SUM(Supuestos!F5:F15) -> 9628
A17: 📌 La inversión se amortiza según el nº de años definido en Supuestos (F27). La cuota anual aparece en el P&L.
